soduco_geonetwork/api_wrapper/__init__.py
soduco_geonetwork/api_wrapper/config.py
soduco_geonetwork/api_wrapper/dataset.py
soduco_geonetwork/api_wrapper/geonetwork.py
soduco_geonetwork/api_wrapper/helpers.py
soduco_geonetwork/api_wrapper/xml_composers.py
soduco_geonetwork/api_wrapper/xmltemplates/dataset_iso19115.xml
soduco_geonetwork/api_wrapper/yaml_to_xml.py
soduco_geonetwork/cli/__init__.py
soduco_geonetwork/cli/cli.py
soduco_geonetwork-0.1.0a0.dist-info/entry_points.txt
soduco_geonetwork-0.1.0a0.dist-info/COPYING
soduco_geonetwork-0.1.0a0.dist-info/COPYING.LESSER
soduco_geonetwork-0.1.0a0.dist-info/WHEEL
soduco_geonetwork-0.1.0a0.dist-info/METADATA
soduco_geonetwork-0.1.0a0.dist-info/RECORD
